biotext/__init__.py
biotext/aminocode.py
biotext/dnabits.py
biotext/sweeptex.py
biotext/sweeptex_emb.py
biotext/internal/__init__.py
biotext/internal/count_occurrences.py
biotext/internal/create_seqrecord_list.py
biotext/internal/explode_list.py
biotext/internal/map_docs_to_words.py
biotext/internal/map_words_to_docs.py
biotext/internal/parallelization.py
biotext/internal/split_array.py
biotext/internal/tokenize.py
biotext/internal/sweep/__init__.py
biotext/internal/sweep/fasta_to_sweep.py
biotext/internal/sweep/internal/__init__.py
biotext/internal/sweep/internal/aa_to_num.py
biotext/internal/sweep/internal/count_occ.py
biotext/internal/sweep/internal/lambert_w.py
biotext/internal/sweep/internal/load_matrix_from_path.py
biotext/internal/sweep/internal/nt_to_num.py
biotext/internal/sweep/internal/scan_mask.py
biotext/internal/sweep/internal/transform_with_lambert_w.py
biotext/internal/sweep/utils/__init__.py
biotext/internal/sweep/utils/create_proj_mat.py
biotext/internal/sweep/utils/create_sweep_masks.py
biotext/internal/sweep/utils/fastaread.py
biotext/internal/sweep/utils/orthrand.py
biotext-2025.6.27.dist-info/licenses/LICENSE.txt
biotext-2025.6.27.dist-info/METADATA
biotext-2025.6.27.dist-info/WHEEL
biotext-2025.6.27.dist-info/top_level.txt
biotext-2025.6.27.dist-info/RECORD
