Metadata-Version: 2.4
Name: biotext
Version: 2025.6.27
Summary: Biotext bridges Bioinformatics and NLP by encoding data into a Biological Sequence-Like format. Combined with the SWeeP method, it supports vector operations for efficient analysis.
Author: Diogo de Jesus Soares Machado, Roberto Tadeu Raittz
License: Custom Non-Commercial License
License-File: LICENSE.txt
Requires-Dist: biopython==1.85
Requires-Dist: h5py==3.13.0
Requires-Dist: joblib==1.4.2
Requires-Dist: numpy==2.2.4
Requires-Dist: scipy==1.15.2
Requires-Dist: tqdm==4.67.1
Dynamic: author
Dynamic: description
Dynamic: description-content-type
Dynamic: license
Dynamic: license-file
Dynamic: requires-dist
Dynamic: summary
